{
  "id": "bhavani_stotram",
  "title_en": "Bhavani Stotram",
  "title_hi": "भवानी स्तोत्रम्",
  "deity": "devi",
  "author": "Adi Shankaracharya",
  "type": "stotram",
  "total_verses": 12,
  "sections": [
    "stotram"
  ],
  "description_en": "Bhavani Stotram is a devotional hymn composed by Adi Shankaracharya in praise of Goddess Bhavani, a form of Goddess Parvati. The stotram consists of 12 verses in which the devotee expresses complete surrender and helplessness, declaring that he has no father, no mother, no relative, and no benefactor other than Goddess Bhavani. Each verse ends with the refrain 'Na Tato Na Mata Na Bandhu Na Data, Tvameka Gatis Tvameka Vidhata' — seeking the Goddess as the sole refuge and protector. It is a powerful expression of Sharanagati (total surrender) to the Divine Mother.",
  "description_hi": "भवानी स्तोत्रम् आदि शंकराचार्य द्वारा रचित देवी भवानी की स्तुति में एक भक्तिपूर्ण स्तोत्र है। भवानी देवी पार्वती का एक रूप हैं। इस स्तोत्र में 12 श्लोक हैं जिनमें भक्त पूर्ण समर्पण और असहायता व्यक्त करता है, यह कहते हुए कि उसका कोई पिता, माता, बंधु या दाता नहीं है, सिवाय देवी भवानी के। प्रत्येक श्लोक का अंत 'न तातो न माता न बंधुर्न दाता' से होता है — देवी को एकमात्र शरण और रक्षक के रूप में प्रार्थना करते हुए। यह शरणागति का एक अत्यंत शक्तिशाली भाव है।",
  "verses": [
    {
      "verse_number": 1,
      "section": "stotram",
      "hindi_text": "न तातो न माता न बन्धुर्न दाता\nन पुत्रो न पुत्री न भृत्यो न भर्ता।\nन जाया न विद्या न वृत्तिर्ममैव\nगतिस्त्वं गतिस्त्वं त्वमेका भवानि॥",
      "transliteration": "Na Tato Na Mata Na Bandhur Na Data\nNa Putro Na Putri Na Bhrutyo Na Bharta|\nNa Jaya Na Vidya Na Vruttir Mamaiva\nGatistvam Gatistvam Tvameka Bhavani||",
      "word_by_word": {
        "न": "not/no",
        "तातो": "father",
        "माता": "mother",
        "बन्धुः": "relative/friend",
        "दाता": "benefactor/giver",
        "पुत्रो": "son",
        "पुत्री": "daughter",
        "भृत्यो": "servant",
        "भर्ता": "husband/lord",
        "जाया": "wife",
        "विद्या": "knowledge/learning",
        "वृत्तिः": "livelihood/occupation",
        "ममैव": "mine indeed",
        "गतिः": "refuge/goal/path",
        "त्वम्": "you",
        "एका": "alone/only one",
        "भवानि": "O Bhavani"
      },
      "meaning_en": "I have no father, no mother, no relative, no benefactor. I have no son, no daughter, no servant, no husband. I have no wife, no knowledge, no livelihood of my own. You alone are my refuge, You alone are my refuge, O Bhavani!",
      "meaning_hi": "मेरा कोई पिता नहीं, कोई माता नहीं, कोई बंधु नहीं, कोई दाता नहीं। मेरा कोई पुत्र नहीं, कोई पुत्री नहीं, कोई सेवक नहीं, कोई स्वामी नहीं। मेरी कोई पत्नी नहीं, कोई विद्या नहीं, कोई जीविका नहीं। हे भवानी! तू ही मेरी एकमात्र गति है, तू ही मेरी एकमात्र गति है।",
      "modern_context_en": "In today's world where relationships are often transactional and material securities are uncertain, this verse reminds us that all worldly supports are temporary. True and permanent refuge lies only in the Divine. This verse is especially meaningful for those facing loneliness, loss of family, or financial hardship.",
      "modern_context_hi": "आज के युग में जहाँ रिश्ते अक्सर स्वार्थपूर्ण होते हैं और भौतिक सुरक्षा अनिश्चित होती है, यह श्लोक हमें स्मरण दिलाता है कि सभी सांसारिक आश्रय अस्थायी हैं। सच्चा और स्थायी आश्रय केवल ईश्वर में है। यह श्लोक उन लोगों के लिए विशेष रूप से अर्थपूर्ण है जो एकाकीपन, परिवार की हानि या आर्थिक कठिनाई का सामना कर रहे हैं।"
    },
    {
      "verse_number": 2,
      "section": "stotram",
      "hindi_text": "भवाब्धावपारे महादुःखभीरु\nपपात प्रकामी प्रलोभी प्रमत्तः।\nकुसंसारपाशप्रबद्धः सदाहं\nगतिस्त्वं गतिस्त्वं त्वमेका भवानि॥",
      "transliteration": "Bhavaabdhavapaare Mahaaduhkhabhiru\nPapaata Prakaami Pralobhi Pramattah|\nKusamsaarapaashabaddah Sadaaham\nGatistvam Gatistvam Tvameka Bhavani||",
      "word_by_word": {
        "भवाब्धौ": "in the ocean of worldly existence",
        "अपारे": "boundless/endless",
        "महादुःखभीरु": "fearing great suffering",
        "पपात": "have fallen",
        "प्रकामी": "full of desires/lust",
        "प्रलोभी": "full of greed",
        "प्रमत्तः": "intoxicated/deluded",
        "कुसंसार": "wicked worldly life",
        "पाश": "noose/bond",
        "प्रबद्धः": "tightly bound",
        "सदा": "always",
        "अहम्": "I",
        "गतिः": "refuge",
        "त्वम्": "you",
        "एका": "alone",
        "भवानि": "O Bhavani"
      },
      "meaning_en": "I have fallen into the boundless ocean of worldly existence, fearing great suffering. I am filled with desires, greed, and delusion. I am always tightly bound by the nooses of this wicked worldly life. You alone are my refuge, You alone are my refuge, O Bhavani!",
      "meaning_hi": "मैं इस अपार संसार-सागर में गिर गया हूँ, महादुःख से भयभीत हूँ। मैं कामना, लोभ और मोह से भरा हूँ। मैं सदा इस दुष्ट संसार के पाश में कसकर बँधा हूँ। हे भवानी! तू ही मेरी एकमात्र गति है, तू ही मेरी एकमात्र गति है।",
      "modern_context_en": "This verse speaks to the modern human condition where people are trapped in the cycles of desire, greed, and distraction — whether through social media, consumerism, or addictions. It acknowledges human weakness and implores divine grace for liberation from these binding forces.",
      "modern_context_hi": "यह श्लोक आधुनिक मानव की स्थिति को दर्शाता है जहाँ लोग इच्छा, लालच और विकर्षण के चक्रों में फँसे हैं — चाहे सोशल मीडिया हो, उपभोक्तावाद हो, या लत हो। यह मानवीय दुर्बलता को स्वीकार करता है और इन बंधनों से मुक्ति के लिए दिव्य कृपा की प्रार्थना करता है।"
    },
    {
      "verse_number": 3,
      "section": "stotram",
      "hindi_text": "न जानामि दानं न च ध्यानयोगं\nन जानामि तन्त्रं न च स्तोत्रमन्त्रम्।\nन जानामि पूजां न च न्यासयोगं\nगतिस्त्वं गतिस्त्वं त्वमेका भवानि॥",
      "transliteration": "Na Jaanaami Daanam Na Cha Dhyaanayogam\nNa Jaanaami Tantram Na Cha Stotramantram|\nNa Jaanaami Puujaam Na Cha Nyaasayogam\nGatistvam Gatistvam Tvameka Bhavani||",
      "word_by_word": {
        "न": "not",
        "जानामि": "I know",
        "दानं": "charity/giving",
        "ध्यान": "meditation",
        "योगं": "yoga/union",
        "तन्त्रं": "tantra/ritual scripture",
        "स्तोत्र": "hymn/praise",
        "मन्त्रम्": "sacred chant/mantra",
        "पूजां": "worship/ritual offering",
        "न्यास": "placement of mantras on body",
        "गतिः": "refuge",
        "त्वम्": "you",
        "एका": "alone",
        "भवानि": "O Bhavani"
      },
      "meaning_en": "I do not know charity, nor do I know the yoga of meditation. I do not know Tantra, nor do I know hymns or mantras. I do not know ritual worship, nor do I know the practice of Nyasa. You alone are my refuge, You alone are my refuge, O Bhavani!",
      "meaning_hi": "मैं दान को नहीं जानता, न ध्यानयोग को जानता हूँ। मैं तंत्र को नहीं जानता, न स्तोत्र और मंत्र को जानता हूँ। मैं पूजा को नहीं जानता, न न्यासयोग को जानता हूँ। हे भवानी! तू ही मेरी एकमात्र गति है, तू ही मेरी एकमात्र गति है।",
      "modern_context_en": "In an age where spiritual practices have become commercialized and complex, this verse reassures that sincere surrender to the Divine is sufficient. Even without elaborate rituals, mantras, or spiritual techniques, pure devotion and surrender can lead to divine grace. This is an encouraging message for the spiritually unlearned.",
      "modern_context_hi": "एक ऐसे युग में जहाँ आध्यात्मिक साधनाएँ जटिल और व्यावसायिक हो गई हैं, यह श्लोक आश्वस्त करता है कि ईश्वर के प्रति सच्चा समर्पण पर्याप्त है। विस्तृत अनुष्ठानों, मंत्रों या आध्यात्मिक तकनीकों के बिना भी, शुद्ध भक्ति और समर्पण दिव्य कृपा की ओर ले जा सकता है।"
    },
    {
      "verse_number": 4,
      "section": "stotram",
      "hindi_text": "न जानामि पुण्यं न जानामि तीर्थं\nन जानामि मुक्तिं लयं वा कदाचित्।\nन जानामि भक्तिं व्रतं वापि मातः\nगतिस्त्वं गतिस्त्वं त्वमेका भवानि॥",
      "transliteration": "Na Jaanaami Punyam Na Jaanaami Teertham\nNa Jaanaami Muktim Layam Vaa Kadaachit|\nNa Jaanaami Bhaktim Vratam Vaapi Maatah\nGatistvam Gatistvam Tvameka Bhavani||",
      "word_by_word": {
        "न": "not",
        "जानामि": "I know",
        "पुण्यं": "merit/virtuous deeds",
        "तीर्थं": "pilgrimage/sacred place",
        "मुक्तिं": "liberation/moksha",
        "लयं": "dissolution/merging",
        "वा": "or",
        "कदाचित्": "ever/at any time",
        "भक्तिं": "devotion",
        "व्रतं": "vow/fasting",
        "वापि": "also/even",
        "मातः": "O Mother",
        "गतिः": "refuge",
        "त्वम्": "you",
        "एका": "alone",
        "भवानि": "O Bhavani"
      },
      "meaning_en": "I do not know virtuous deeds, nor do I know pilgrimage to sacred places. I have never known liberation or dissolution into the Divine. I do not know devotion or religious vows, O Mother. You alone are my refuge, You alone are my refuge, O Bhavani!",
      "meaning_hi": "मैं पुण्य को नहीं जानता, न तीर्थयात्रा को जानता हूँ। मुझे मुक्ति या लय का भी कभी ज्ञान नहीं हुआ। हे माँ! मैं भक्ति और व्रत को भी नहीं जानता। हे भवानी! तू ही मेरी एकमात्र गति है, तू ही मेरी एकमात्र गति है।",
      "modern_context_en": "Many people in modern times feel spiritually inadequate — they have not visited holy places, do not follow religious vows, and are uncertain about concepts like liberation. This verse validates such feelings and reminds us that the Mother's grace transcends all rituals and spiritual accomplishments.",
      "modern_context_hi": "आधुनिक समय में कई लोग आध्यात्मिक रूप से अपर्याप्त महसूस करते हैं — उन्होंने पवित्र स्थानों की यात्रा नहीं की, धार्मिक व्रत नहीं रखते, और मुक्ति जैसी अवधारणाओं के बारे में अनिश्चित हैं। यह श्लोक ऐसी भावनाओं को मान्य करता है और याद दिलाता है कि माँ की कृपा सभी अनुष्ठानों और आध्यात्मिक उपलब्धियों से परे है।"
    },
    {
      "verse_number": 5,
      "section": "stotram",
      "hindi_text": "कुकर्मी कुसङ्गी कुबुद्धिः कुदासः\nकुलाचारहीनः कदाचारलीनः।\nकुदृष्टिः कुवाक्यप्रबन्धः सदाहं\nगतिस्त्वं गतिस्त्वं त्वमेका भवानि॥",
      "transliteration": "Kukarmi Kusangi Kubuddhih Kudasah\nKulaachaaraheenah Kadaachaaraleenah|\nKudrushthih Kuvakyaprabandhah Sadaaham\nGatistvam Gatistvam Tvameka Bhavani||",
      "word_by_word": {
        "कुकर्मी": "one who performs evil deeds",
        "कुसङ्गी": "one who keeps bad company",
        "कुबुद्धिः": "one with perverted/wicked intellect",
        "कुदासः": "wicked servant",
        "कुलाचारहीनः": "devoid of family traditions and good conduct",
        "कदाचारलीनः": "immersed in evil conduct",
        "कुदृष्टिः": "one with evil sight/perception",
        "कुवाक्य": "evil words/speech",
        "प्रबन्धः": "one given to/engaged in",
        "सदा": "always",
        "अहम्": "I",
        "गतिः": "refuge",
        "त्वम्": "you",
        "एका": "alone",
        "भवानि": "O Bhavani"
      },
      "meaning_en": "I am one who performs evil deeds, keeps bad company, has a wicked intellect, and is a wicked servant. I am devoid of family traditions and good conduct, immersed in evil behavior. I have an evil perception and am always engaged in wicked speech. You alone are my refuge, You alone are my refuge, O Bhavani!",
      "meaning_hi": "मैं बुरे कर्म करने वाला, बुरी संगत रखने वाला, दुष्ट बुद्धि वाला और कुदास हूँ। मैं कुलाचार से रहित और दुराचार में लीन हूँ। मेरी दृष्टि और वचन भी कुटिल हैं। हे भवानी! तू ही मेरी एकमात्र गति है, तू ही मेरी एकमात्र गति है।",
      "modern_context_en": "This verse is a profound confession of human moral failings. In modern society, where peer pressure leads people into bad habits, wrong associations, and morally questionable behavior, this verse teaches humility and honest self-reflection. It shows that even the most fallen can seek divine refuge without shame.",
      "modern_context_hi": "यह श्लोक मानवीय नैतिक कमजोरियों की एक गहरी स्वीकृति है। आधुनिक समाज में जहाँ साथियों का दबाव लोगों को बुरी आदतों, गलत संगति और नैतिक रूप से संदिग्ध व्यवहार में ले जाता है, यह श्लोक विनम्रता और ईमानदार आत्म-चिंतन सिखाता है।"
    },
    {
      "verse_number": 6,
      "section": "stotram",
      "hindi_text": "प्रजेशं रमेशं महेशं सुरेशं\nदिनेशं निशीथेश्वरं वा कदाचित्।\nन जानामि चान्यत् सदाहं शरण्ये\nगतिस्त्वं गतिस्त्वं त्वमेका भवानि॥",
      "transliteration": "Prajlesham Ramesham Mahesham Suresham\nDinesham Nishitheeshvaram Vaa Kadaachit|\nNa Jaanaami Chaanyat Sadaaham Sharanye\nGatistvam Gatistvam Tvameka Bhavani||",
      "word_by_word": {
        "प्रजेशं": "Brahma, lord of creation/beings",
        "रमेशं": "Vishnu, lord of Lakshmi",
        "महेशं": "Shiva, the great lord",
        "सुरेशं": "Indra, lord of gods",
        "दिनेशं": "Sun, lord of day",
        "निशीथेश्वरं": "Moon, lord of night",
        "वा": "or",
        "कदाचित्": "ever",
        "न": "not",
        "जानामि": "I know",
        "चान्यत्": "anything else",
        "सदा": "always",
        "अहम्": "I",
        "शरण्ये": "O refuge/protector",
        "गतिः": "refuge",
        "त्वम्": "you",
        "एका": "alone",
        "भवानि": "O Bhavani"
      },
      "meaning_en": "I do not know Brahma the lord of creation, nor Vishnu the lord of Lakshmi, nor Shiva the great lord, nor Indra the lord of gods. I do not know the Sun lord of the day, or the Moon lord of the night. I do not know anything else, O refuge of all. You alone are my refuge, You alone are my refuge, O Bhavani!",
      "meaning_hi": "मैं प्रजापति ब्रह्मा को नहीं जानता, न विष्णु को, न महेश्वर को, न देवताओं के राजा इंद्र को। मैं दिन के स्वामी सूर्य को नहीं जानता, न रात के स्वामी चंद्रमा को। हे शरण्ये! मैं किसी और को नहीं जानता। हे भवानी! तू ही मेरी एकमात्र गति है।",
      "modern_context_en": "This verse expresses exclusive devotion to the Divine Mother above all other gods and cosmic forces. In modern pluralistic spirituality, this verse reminds us that single-pointed devotion (Ekagra bhakti) to one's chosen deity is a valid and powerful path. It is a declaration of supreme love and surrender.",
      "modern_context_hi": "यह श्लोक सभी अन्य देवताओं और ब्रह्मांडीय शक्तियों से ऊपर दिव्य माता के प्रति एकान्त भक्ति व्यक्त करता है। आधुनिक बहुलवादी आध्यात्मिकता में, यह श्लोक याद दिलाता है कि अपने इष्ट देवता के प्रति एकाग्र भक्ति एक वैध और शक्तिशाली मार्ग है।"
    },
    {
      "verse_number": 7,
      "section": "stotram",
      "hindi_text": "विवादे विषादे प्रमादे प्रवासे\nजले चानले पर्वते शत्रुमध्ये।\nअरण्ये शरण्ये सदा मां प्रपाहि\nगतिस्त्वं गतिस्त्वं त्वमेका भवानि॥",
      "transliteration": "Vivaade Vishaade Pramaade Pravaase\nJale Chaanale Parvate Shatrumadhye|\nAranye Sharanye Sadaa Maam Prapaahi\nGatistvam Gatistvam Tvameka Bhavani||",
      "word_by_word": {
        "विवादे": "in dispute/conflict",
        "विषादे": "in grief/depression",
        "प्रमादे": "in negligence/danger",
        "प्रवासे": "in travel/away from home",
        "जले": "in water",
        "चानले": "and in fire",
        "पर्वते": "on mountain",
        "शत्रुमध्ये": "amidst enemies",
        "अरण्ये": "in forest/wilderness",
        "शरण्ये": "O refuge/protector",
        "सदा": "always",
        "मां": "me",
        "प्रपाहि": "protect completely",
        "गतिः": "refuge",
        "त्वम्": "you",
        "एका": "alone",
        "भवानि": "O Bhavani"
      },
      "meaning_en": "In dispute, in grief, in danger, in travel away from home; in water, in fire, on a mountain, amidst enemies; in the forest — O refuge of all, always protect me completely. You alone are my refuge, You alone are my refuge, O Bhavani!",
      "meaning_hi": "विवाद में, विषाद में, प्रमाद में, परदेश में; जल में, अग्नि में, पर्वत पर, शत्रुओं के बीच में; वन में — हे शरण्ये! सदा मेरी पूर्ण रक्षा करो। हे भवानी! तू ही मेरी एकमात्र गति है, तू ही मेरी एकमात्र गति है।",
      "modern_context_en": "This verse is highly relevant in the modern world where people face conflicts in workplaces, depression and anxiety, accidents, travel emergencies, and hostile environments. It is a powerful prayer for protection in all dangerous and challenging situations. Reciting this verse instills courage and trust in divine protection.",
      "modern_context_hi": "यह श्लोक आधुनिक दुनिया में अत्यंत प्रासंगिक है जहाँ लोग कार्यस्थल पर संघर्ष, अवसाद और चिंता, दुर्घटनाओं, यात्रा आपात स्थितियों और शत्रुतापूर्ण वातावरण का सामना करते हैं। यह सभी खतरनाक और चुनौतीपूर्ण परिस्थितियों में सुरक्षा के लिए एक शक्तिशाली प्रार्थना है।"
    },
    {
      "verse_number": 8,
      "section": "stotram",
      "hindi_text": "अनाथो दरिद्रो जरारोगयुक्तो\nमहाक्षीणदीनः सदा जाड्यवक्त्रः।\nविपत्तौ प्रविष्टः प्रनष्टः सदाहं\nगतिस्त्वं गतिस्त्वं त्वमेका भवानि॥",
      "transliteration": "Anaatho Daridro Jaraarogayukto\nMahaaksheenadeenah Sadaa Jaadyavaktrah|\nVipattau Pravishtah Pranashthah Sadaaham\nGatistvam Gatistvam Tvameka Bhavani||",
      "word_by_word": {
        "अनाथः": "orphan/one without protector",
        "दरिद्रः": "poor/destitute",
        "जरा": "old age",
        "रोग": "disease/illness",
        "युक्तः": "afflicted with",
        "महाक्षीण": "greatly weakened/emaciated",
        "दीनः": "pitiable/helpless",
        "सदा": "always",
        "जाड्यवक्त्रः": "dull/stupid in speech",
        "विपत्तौ": "in calamity/misfortune",
        "प्रविष्टः": "entered/fallen into",
        "प्रनष्टः": "completely lost/ruined",
        "अहम्": "I",
        "गतिः": "refuge",
        "त्वम्": "you",
        "एका": "alone",
        "भवानि": "O Bhavani"
      },
      "meaning_en": "I am an orphan, destitute, afflicted with old age and disease, greatly weakened and pitiable, always dull in speech. I have fallen into calamity and am completely ruined. You alone are my refuge, You alone are my refuge, O Bhavani!",
      "meaning_hi": "मैं अनाथ हूँ, दरिद्र हूँ, वृद्धावस्था और रोग से पीड़ित हूँ, अत्यंत क्षीण और दीन हूँ, सदा मंद-वाक् हूँ। मैं विपत्ति में पड़ गया हूँ और पूर्णतः नष्ट हो गया हूँ। हे भवानी! तू ही मेरी एकमात्र गति है, तू ही मेरी एकमात्र गति है।",
      "modern_context_en": "This verse speaks to those suffering from chronic illness, poverty, loneliness, and the loss of all worldly supports. In modern healthcare and social crises, where many feel abandoned by society, this verse offers the ultimate comfort — that the Divine Mother never abandons her children, no matter how fallen or broken they may be.",
      "modern_context_hi": "यह श्लोक उन लोगों से बात करता है जो पुरानी बीमारी, गरीबी, एकाकीपन और सभी सांसारिक आश्रयों की हानि से पीड़ित हैं। आधुनिक स्वास्थ्य सेवा और सामाजिक संकटों में, जहाँ कई लोग समाज द्वारा परित्यक्त महसूस करते हैं, यह श्लोक परम सांत्वना प्रदान करता है।"
    },
    {
      "verse_number": 9,
      "section": "stotram",
      "hindi_text": "सुरासुरैर्वन्दितपादपद्मे\nशिवे दयाद्रार्द्रहृदे प्रसन्ने।\nप्रभाते सदा मोक्षमार्गे प्रवृत्ते\nगतिस्त्वं गतिस्त्वं त्वमेका भवानि॥",
      "transliteration": "Suraasurairvandita Paadapadme\nShive Dayaadraardrahride Prasanne|\nPrabhaate Sadaa Mokshamaarge Pravrutte\nGatistvam Gatistvam Tvameka Bhavani||",
      "word_by_word": {
        "सुरासुरैः": "by gods and demons",
        "वन्दित": "worshipped/adored",
        "पादपद्मे": "lotus feet",
        "शिवे": "O auspicious one",
        "दया": "compassion",
        "द्रार्द्र": "melted/moved with",
        "हृदे": "heart",
        "प्रसन्ने": "one who is pleased/gracious",
        "प्रभाते": "at dawn/in the morning",
        "सदा": "always",
        "मोक्षमार्गे": "on the path of liberation",
        "प्रवृत्ते": "engaged/active",
        "गतिः": "refuge",
        "त्वम्": "you",
        "एका": "alone",
        "भवानि": "O Bhavani"
      },
      "meaning_en": "O auspicious Goddess, whose lotus feet are worshipped by both gods and demons, whose heart melts with compassion, who is ever gracious; who is always engaged on the path of liberation at every dawn — You alone are my refuge, You alone are my refuge, O Bhavani!",
      "meaning_hi": "हे शिवे! जिनके चरण-कमल देवताओं और असुरों दोनों द्वारा पूजे जाते हैं, जिनका हृदय दया से आर्द्र है, जो सदा प्रसन्न हैं; जो प्रभात में सदा मोक्षमार्ग में प्रवृत्त हैं — हे भवानी! तू ही मेरी एकमात्र गति है, तू ही मेरी एकमात्र गति है।",
      "modern_context_en": "This verse reminds us of the universal nature of the Divine Mother — she is worshipped by all, both the virtuous and the fallen. Her compassion is limitless and she is always active in guiding souls toward liberation. In modern spiritual seeking, this verse gives hope that the divine path to liberation is always open.",
      "modern_context_hi": "यह श्लोक दिव्य माता की सार्वभौमिक प्रकृति की याद दिलाता है — उनकी पूजा सभी करते हैं, चाहे धर्मी हों या पतित। उनकी करुणा असीमित है और वे सदा आत्माओं को मुक्ति की ओर मार्गदर्शन करने में सक्रिय हैं।"
    },
    {
      "verse_number": 10,
      "section": "stotram",
      "hindi_text": "इदं स्तोत्रं मातुर्लिखितं महेशि\nत्रिसंध्यं पठेद्यो नरः शुद्धचित्तः।\nस पुत्रैः पशुभ्यः स्मृद्धिमान् भूमिमान् च\nलभेदेव मातुः प्रसादेन मुक्तिम्॥",
      "transliteration": "Idam Stotram Maatur Likhitam Maheshi\nTrisandhyam Patheddyo Narah Shuddhachitta|\nSa Putraih Pashubhyah Samriddhimaan Bhumimaan Cha\nLabhedevamaatuhu Prasaadena Muktim||",
      "word_by_word": {
        "इदम्": "this",
        "स्तोत्रम्": "hymn/prayer",
        "मातुः": "of the Mother",
        "लिखितम्": "written",
        "महेशि": "O great Goddess",
        "त्रिसंध्यम्": "three times daily (at dawn, noon, dusk)",
        "पठेत्": "recites",
        "यः": "who",
        "नरः": "person/man",
        "शुद्धचित्तः": "with pure mind",
        "पुत्रैः": "with sons/children",
        "पशुभ्यः": "with cattle/wealth",
        "समृद्धिमान्": "prosperous",
        "भूमिमान्": "possessing land",
        "लभेत्": "obtains",
        "एव": "indeed",
        "प्रसादेन": "by grace",
        "मुक्तिम्": "liberation"
      },
      "meaning_en": "This hymn to the Mother, O great Goddess, composed in writing — whoever recites it three times daily (at dawn, noon, and dusk) with a pure mind, that person becomes prosperous with children and cattle and land, and indeed by the grace of the Mother, attains liberation.",
      "meaning_hi": "हे महेशि! माता की यह स्तुति जो लिखित में रचित है — जो कोई भी शुद्ध चित्त से तीनों संध्याओं में इसका पाठ करता है, वह व्यक्ति पुत्रों, पशु-धन और भूमि से समृद्ध होता है और माता की कृपा से मुक्ति को प्राप्त करता है।",
      "modern_context_en": "This verse describes the phala-shruti (fruits of recitation) of the stotram. In modern terms, regular recitation of this hymn with sincerity can bring both material prosperity (family wellbeing, financial stability) and spiritual liberation. It motivates consistent daily practice of devotion.",
      "modern_context_hi": "यह श्लोक स्तोत्र के पाठ के फल (फलश्रुति) का वर्णन करता है। आधुनिक संदर्भ में, इस स्तोत्र का नियमित और सच्चे मन से पाठ करने से भौतिक समृद्धि (पारिवारिक कल्याण, आर्थिक स्थिरता) और आध्यात्मिक मुक्ति दोनों प्राप्त हो सकते हैं।"
    },
    {
      "verse_number": 11,
      "section": "stotram",
      "hindi_text": "शरीरं सुरूपं तथा वा कलत्रं\nयशश्चारु चित्रं धनं मेरुतुल्यम्।\nमनश्चेन्न लग्नं गुरोरङ्घ्रिपद्मे\nततः किं ततः किं ततः किं ततः किम्॥",
      "transliteration": "Shariram Suroopam Tathaa Vaa Kalatram\nYashashchaaru Chitram Dhanam Merutulyam|\nManashchenna Lagnam Guroranghripadme\nTatah Kim Tatah Kim Tatah Kim Tatah Kim||",
      "word_by_word": {
        "शरीरम्": "body",
        "सुरूपम्": "beautiful form",
        "तथा": "also",
        "वा": "or",
        "कलत्रम्": "spouse/wife",
        "यशः": "fame",
        "चारु": "beautiful/pleasant",
        "चित्रम्": "wonderful",
        "धनम्": "wealth",
        "मेरुतुल्यम्": "equal to Mount Meru",
        "मनः": "mind",
        "चेत्": "if",
        "न": "not",
        "लग्नम्": "attached/engaged",
        "गुरोः": "of the Guru",
        "अङ्घ्रिपद्मे": "lotus feet",
        "ततः": "then",
        "किम्": "what use/what of it"
      },
      "meaning_en": "If one has a beautiful body, a wonderful spouse, excellent fame, and wealth equal to Mount Meru — but if the mind is not engaged at the lotus feet of the Guru, then what of it? What of it? What of it? What of it?",
      "meaning_hi": "यदि किसी के पास सुंदर शरीर हो, उत्तम पत्नी हो, अद्भुत यश हो और मेरु पर्वत के समान धन हो — लेकिन यदि मन गुरु के चरणकमल में नहीं लगा है, तो इससे क्या? इससे क्या? इससे क्या? इससे क्या?",
      "modern_context_en": "This verse, often attributed as part of the extended Bhavani Stotram tradition, highlights the futility of all material achievements without spiritual anchoring. In today's success-obsessed culture, it reminds us that beauty, fame, a good partner, and immense wealth mean nothing without inner spiritual connection and wisdom.",
      "modern_context_hi": "यह श्लोक, जो विस्तृत भवानी स्तोत्र परंपरा का हिस्सा माना जाता है, आध्यात्मिक आधार के बिना सभी भौतिक उपलब्धियों की व्यर्थता को उजागर करता है। आज की सफलता-केंद्रित संस्कृति में, यह याद दिलाता है कि सुंदरता, प्रसिद्धि, अच्छा साथी और विशाल धन — आंतरिक आध्यात्मिक जुड़ाव के बिना निरर्थक हैं।"
    },
    {
      "verse_number": 12,
      "section": "stotram",
      "hindi_text": "न मोक्षस्य काङ्क्षा भवे मे न सङ्गः\nयशः प्रार्थनाया न जाने न भोगम्।\nअखण्डैकवाक्यं सदाहं प्रार्थये\nगतिस्त्वं गतिस्त्वं त्वमेका भवानि॥",
      "transliteration": "Na Mokhasya Kaankshaa Bhave Me Na Sangah\nYashah Praarthanaaayaa Na Jaane Na Bhogam|\nAkhandaikavaakyam Sadaaham Praarthaye\nGatistvam Gatistvam Tvameka Bhavani||",
      "word_by_word": {
        "न": "not",
        "मोक्षस्य": "of liberation",
        "काङ्क्षा": "desire/longing",
        "भवे": "in existence/world",
        "मे": "my",
        "सङ्गः": "attachment",
        "यशः": "fame",
        "प्रार्थनायाः": "of prayer/desire",
        "न जाने": "I do not know",
        "भोगम्": "enjoyment/pleasure",
        "अखण्ड": "unbroken/undivided",
        "एकवाक्यम्": "with one statement/single utterance",
        "सदा": "always",
        "अहम्": "I",
        "प्रार्थये": "I pray",
        "गतिः": "refuge",
        "त्वम्": "you",
        "एका": "alone",
        "भवानि": "O Bhavani"
      },
      "meaning_en": "I have no desire for liberation, nor attachment to worldly existence. I do not know the desire for fame, nor do I seek enjoyment and pleasure. With an undivided, single-pointed declaration, I always pray: You alone are my refuge, You alone are my refuge, O Bhavani!",
      "meaning_hi": "मुझे न मोक्ष की इच्छा है, न संसार में आसक्ति है। मैं यश की प्रार्थना नहीं जानता, न मुझे भोग की इच्छा है। अखंड एकवाक्य से मैं सदा प्रार्थना करता हूँ — हे भवानी! तू ही मेरी एकमात्र गति है, तू ही मेरी एकमात्र गति है।",
      "modern_context_en": "This concluding verse represents the pinnacle of non-transactional devotion (Nishkama Bhakti). The devotee asks for nothing — not even liberation — but simply surrenders completely to the Mother. In modern spiritual practice, this represents the highest form of prayer: desireless love and total surrender to the Divine. It is the ultimate antidote to the goal-oriented, achievement-driven mindset of contemporary life.",
      "modern_context_hi": "यह अंतिम श्लोक निष्काम भक्ति की पराकाष्ठा का प्रतिनिधित्व करता है। भक्त कुछ भी नहीं माँगता — यहाँ तक कि मोक्ष भी नहीं — बल्कि केवल माता के चरणों में पूर्ण समर्पण करता है। आधुनिक आध्यात्मिक साधना में, यह प्रार्थना का सर्वोच्च रूप है: निष्काम प्रेम और दिव्य शक्ति के प्रति पूर्ण शरणागति।"
    }
  ]
}